streamlit_typed_session/__init__.py
streamlit_typed_session/bases.py
streamlit_typed_session/descriptors.py
streamlit_typed_session/mytypes.py
streamlit_typed_session/providers.py
streamlit_typed_session/py.typed
streamlit_typed_session-0.1.0.post2.dist-info/METADATA
streamlit_typed_session-0.1.0.post2.dist-info/WHEEL
streamlit_typed_session-0.1.0.post2.dist-info/licenses/LICENSE
streamlit_typed_session-0.1.0.post2.dist-info/RECORD
